braglog/__init__.py
braglog/__main__.py
braglog/cli.py
braglog/models.py
braglog/formatters/__init__.py
braglog/formatters/basic.py
braglog/formatters/foldable_html.py
braglog/formatters/html.py
braglog/formatters/json.py
braglog/formatters/markdown.py
braglog-0.5.1.dist-info/licenses/LICENSE
braglog-0.5.1.dist-info/METADATA
braglog-0.5.1.dist-info/WHEEL
braglog-0.5.1.dist-info/entry_points.txt
braglog-0.5.1.dist-info/top_level.txt
braglog-0.5.1.dist-info/RECORD
