Metadata-Version: 2.4
Name: braglog
Version: 0.5.1
Summary: A concise command-line tool for quickly logging daily tasks and milestones, ideal for personal and professional record-keeping.
Project-URL: Homepage, https://github.com/greatbahram/braglog
Project-URL: Changelog, https://github.com/greatbahram/braglog/releases
Project-URL: Issues, https://github.com/greatbahram/braglog/issues
Project-URL: CI, https://github.com/greatbahram/braglog/actions
Requires-Python: >=3.12
License-File: LICENSE
Requires-Dist: click-default-group>=1.2.4
Requires-Dist: click>=8.1.8
Requires-Dist: peewee>=3.17.9
Requires-Dist: dateparser>=1.2.1
Provides-Extra: dev
Requires-Dist: mkdocs-material>=9.6.11; extra == "dev"
Requires-Dist: pre-commit>=4.2.0; extra == "dev"
Requires-Dist: pytest>=8.3.5; extra == "dev"
Requires-Dist: ruff>=0.11.2; extra == "dev"
Dynamic: license-file
